yydict/__init__.py
yydict/yy_dict.py
yydict-0.0.2.dist-info/LICENSE
yydict-0.0.2.dist-info/METADATA
yydict-0.0.2.dist-info/WHEEL
yydict-0.0.2.dist-info/top_level.txt
yydict-0.0.2.dist-info/RECORD
