Metadata-Version: 2.1
Name: yydict
Version: 0.0.2
Summary: YYDict is a dictionary whose items can be set using both attribute and item syntax.
Home-page: https://gitee.com/changyubiao/yydict
Download-URL: https://pypi.python.org/project/yydict/
Author: frank,chang
Author-email: 15769162764@163.com
Keywords: Tools
Classifier: Programming Language :: Python
Classifier: Programming Language :: Python :: 2.7
Classifier: Programming Language :: Python :: 3.6
Classifier: Programming Language :: Python :: 3.7
Classifier: Programming Language :: Python :: 3.8
Classifier: Programming Language :: Python :: 3.9
Classifier: Programming Language :: Python :: 3.10
Classifier: Programming Language :: Python :: 3.11
Classifier: License :: OSI Approved :: MIT License
Classifier: Operating System :: OS Independent
Classifier: Intended Audience :: Developers
Classifier: Topic :: Software Development :: Libraries :: Python Modules
License-File: LICENSE
